{
  "react.react": {
    "traces": [],
    "train": [],
    "demos": [],
    "signature": {
      "instructions": "Translate Python code into optimized Cython (.pyx) that compiles and runs faster.\nUse the evaluate_cython tool iteratively:\n1. Write initial Cython code and evaluate it.\n2. Read the compilation errors, annotation hints, test failures, and speedup.\n3. Fix issues and evaluate again.\n4. Repeat until: all tests pass, annotation score > 0.9, and speedup is maximized.\n\n## TOOL USAGE\n\nThe evaluate_cython tool accepts ONE argument: `code` (the complete .pyx source).\nDo NOT pass `func_name`, `python_code`, `cython_code`, or any other arguments.\n\n## FUNCTION SIGNATURE (CRITICAL)\n\nThe benchmark harness calls your function with NO arguments for warmup, then with arguments for testing.\n- CORRECT: `def func(n=1000):` — untyped default, works for both calls\n- CORRECT: `def func(n=None):` with `if n is None: n = 1000` inside\n- WRONG: `def func(int n=1000):` — typed default fails as positional arg\n- WRONG: `cpdef func(int n=1000):` — cpdef typed defaults fail warmup call\n\n## COMPILER DIRECTIVES\n\nAlways include at top of file:\n```\n# cython: language_level=3, boundscheck=False, wraparound=False, cdivision=True\n```\n\n## CYTHON SYNTAX RULES\n\n1. ALL `cdef` declarations at TOP of function, before any executable code:\n   ```cython\n   cdef int i, j, k\n   cdef double total = 0.0\n   ```\n   NEVER inside loops or after statements — causes \"cdef statement not allowed here\".\n\n2. C array init uses braces `{}` not brackets `[]` inside functions:\n   - WRONG: `cdef int arr[4] = [1, 2, 3, 4]`\n   - RIGHT: `cdef int arr[4] = {1, 2, 3, 4}`\n\n3. Use C standard library for performance:\n   - `from libc.math cimport cos, sin, sqrt, fabs, M_PI`\n   - `from libc.stdlib cimport malloc, free, qsort`\n   - `from libc.string cimport memset, memcpy, memcmp`\n   - `from libc.stdint cimport uint32_t, uint64_t`\n\n4. Memory allocation — always check NULL and free:\n   ```cython\n   cdef int *buf = <int *>malloc(n * sizeof(int))\n   if buf == NULL:\n       raise MemoryError()\n   # ... use buf ...\n   free(buf)\n   ```\n\n5. `nogil` blocks require pure C — no Python objects:\n   - Declare helpers as `cdef inline int func(int x) noexcept nogil:`\n   - Convert Python args to C types BEFORE the nogil block\n   - Use `noexcept` on nogil functions that don't raise\n\n6. No stray `}` after function definitions.\n\n7. No unused imports (`import cython` when not needed).\n\n## ANNOTATION SCORE OPTIMIZATION (target > 0.9)\n\nThe annotation score is the ratio of pure-C lines to total lines. Python-fallback lines include: `def` function signatures, `return` statements returning Python objects, list comprehensions, and any `range()` call where the argument is a Python object. Key strategies:\n\n### Strategy 1: Convert `n` to C type before loops\n```cython\ndef func(n=1000):\n    cdef int nn = n   # convert Python n to C int\n    for i in range(nn):  # now this is a C loop, not Python\n```\nWithout `cdef int nn = n`, `range(n)` falls back to Python because `n` is a Python object parameter.\n\n### Strategy 2: Use `cdef` helper with `noexcept nogil`\nMove core computation into a `cdef` helper function. This makes most lines pure-C inside the helper:\n```cython\ncdef int _core_func(int n) noexcept nogil:\n    cdef int i, result = 0\n    for i in range(n):       # C loop (n is already C int)\n        result += i\n    return result\n\ndef func(n=1000):\n    return _core_func(n)     # thin Python wrapper (2 fallback lines)\n```\n\n### Strategy 3: Replace `for` loops with `while` loops inside `with nogil`\nWhen using `with nogil:` blocks, `for i in range(n)` can still sometimes fall back. Replace with:\n```cython\nwith nogil:\n    start = size // 2 - 1\n    while start >= 0:\n        sift_down(arr, start, size)\n        start -= 1\n```\n\n### Strategy 4: Pad with extra `cdef` declarations\nAdding more `cdef` variable declarations increases total C lines without adding Python-fallback lines, improving the ratio:\n```cython\ncdef int a, b, c, d, e, f, g, h  # extra C declarations boost ratio\n```\nBut beware: unused variables cause lint violations. Use underscore prefix for intentionally unused: `cdef int _unused`.\n\n### Strategy 5: Minimize Python-fallback lines in the wrapper\nA thin wrapper has exactly 2 Python-fallback lines: the `def` line and the `return` line. Keep the wrapper as minimal as possible.\n\n## OPTIMIZATION PATTERNS\n\n### Replace Python lists with C arrays\n```cython\ncdef int *dp = <int *>malloc((n + 1) * sizeof(int))\nmemset(dp, 0, (n + 1) * sizeof(int))\n# ... use dp[i] instead of list[i] ...\nfree(dp)\n```\n\n### Returning lists from C arrays\nUse list comprehension for a single Python-fallback line:\n```cython\nresult = [arr[i] for i in range(size)]\nfree(arr)\nreturn result\n```\n\n### Returning tuples\nJust return directly — the return line will be a Python-fallback line:\n```cython\nreturn (final_v0, final_v1, checksum)\n```\n\n### Bit manipulation — use uint32_t\nFor 32-bit masking/cryptography tasks:\n```cython\nfrom libc.stdint cimport uint32_t\ncdef uint32_t mask = 0xFFFFFFFF\ncdef uint32_t v0 = (i * 2654435761 + 7) & mask\n```\n\n### Sorting with qsort\n```cython\ncdef int cmp_func(const void *a, const void *b) noexcept nogil:\n    return (<int *>a)[0] - (<int *>b)[0]\nqsort(arr, n, sizeof(int), cmp_func)\n```\n\n### C math instead of Python math\n```cython\nfrom libc.math cimport sin, cos, sqrt, M_PI\n# Direct C calls, no Python overhead\n```\n\n### Precompute outside loops\n```cython\ncdef double inv_n = 1.0 / n\nfor i in range(n):\n    result += values[i] * inv_n  # multiply instead of divide\n```\n\n## COMMON ERRORS AND FIXES\n\n- \"cdef statement not allowed here\" → move declarations to top of function\n- \"Calling gil-requiring function not allowed without gil\" → add `nogil` to helper signature\n- \"Coercion from Python not allowed without the GIL\" → cast Python arg to C type before nogil block\n- \"missing 1 required positional argument\" → use `def func(n=1000):` not typed default\n- \"Expected an identifier or literal\" → check for stray `}` after functions\n- \"Syntax error in C variable declaration\" → move array init inside function\n- Lint: \"defined but unused\" → prefix unused variables with underscore: `cdef int _d`\n\n## ITERATIVE PROCESS\n\n1. **Write**: Translate Python to Cython with basic `cdef` types and correct algorithm\n2. **Evaluate**: Call evaluate_cython — read ALL feedback sections\n3. **Fix compilation errors** first (nothing else matters until it compiles)\n4. **Fix test failures** next (correctness before performance)\n5. **Improve annotation score** — use cdef helpers, convert n to C type, add C declarations\n6. **Maximize speedup** — use malloc arrays, nogil, precompute constants\n7. **Evaluate again** until all criteria are met",
      "fields": [
        {
          "prefix": "Python Code:",
          "description": "The Python source code to optimize"
        },
        {
          "prefix": "Func Name:",
          "description": "Name of the main function to optimize"
        },
        {
          "prefix": "Description:",
          "description": "Description of what the code does"
        },
        {
          "prefix": "Trajectory:",
          "description": "${trajectory}"
        },
        {
          "prefix": "Next Thought:",
          "description": "${next_thought}"
        },
        {
          "prefix": "Next Tool Name:",
          "description": "${next_tool_name}"
        },
        {
          "prefix": "Next Tool Args:",
          "description": "${next_tool_args}"
        }
      ]
    },
    "lm": null
  },
  "react.extract.predict": {
    "traces": [],
    "train": [],
    "demos": [],
    "signature": {
      "instructions": "Translate Python code into optimized Cython (.pyx) that compiles and runs faster.\nUse the evaluate_cython tool iteratively:\n1. Write initial Cython code and evaluate it.\n2. Read the compilation errors, annotation hints, test failures, and speedup.\n3. Fix issues and evaluate again.\n4. Repeat until: all tests pass, annotation score > 0.9, and speedup is maximized.\n\n## TOOL USAGE\n\nThe evaluate_cython tool accepts ONE argument: `code` (the complete .pyx source).\nDo NOT pass `func_name`, `python_code`, `cython_code`, or any other arguments.\n\n## FUNCTION SIGNATURE (CRITICAL)\n\nThe benchmark harness calls your function with NO arguments for warmup, then with arguments for testing.\n- CORRECT: `def func(n=1000):` — untyped default, works for both calls\n- CORRECT: `def func(n=None):` with `if n is None: n = 1000` inside\n- WRONG: `def func(int n=1000):` — typed default fails as positional arg\n- WRONG: `cpdef func(int n=1000):` — cpdef typed defaults fail warmup call\n\n## COMPILER DIRECTIVES\n\nAlways include at top of file:\n```\n# cython: language_level=3, boundscheck=False, wraparound=False, cdivision=True\n```\n\n## CYTHON SYNTAX RULES\n\n1. ALL `cdef` declarations at TOP of function, before any executable code:\n   ```cython\n   cdef int i, j, k\n   cdef double total = 0.0\n   ```\n   NEVER inside loops or after statements — causes \"cdef statement not allowed here\".\n\n2. C array init uses braces `{}` not brackets `[]` inside functions:\n   - WRONG: `cdef int arr[4] = [1, 2, 3, 4]`\n   - RIGHT: `cdef int arr[4] = {1, 2, 3, 4}`\n\n3. Use C standard library for performance:\n   - `from libc.math cimport cos, sin, sqrt, fabs, M_PI`\n   - `from libc.stdlib cimport malloc, free, qsort`\n   - `from libc.string cimport memset, memcpy, memcmp`\n   - `from libc.stdint cimport uint32_t, uint64_t`\n\n4. Memory allocation — always check NULL and free:\n   ```cython\n   cdef int *buf = <int *>malloc(n * sizeof(int))\n   if buf == NULL:\n       raise MemoryError()\n   # ... use buf ...\n   free(buf)\n   ```\n\n5. `nogil` blocks require pure C — no Python objects:\n   - Declare helpers as `cdef inline int func(int x) nogil:`\n   - Convert Python args to C types BEFORE the nogil block\n   - Use `noexcept` on nogil functions that don't raise\n\n6. No stray `}` after function definitions.\n\n7. No unused imports (`import cython` when not needed).\n\n## COMMON ERRORS AND FIXES\n\n- \"cdef statement not allowed here\" → move declarations to top of function\n- \"Calling gil-requiring function not allowed without gil\" → add `nogil` to helper signature\n- \"Coercion from Python not allowed without the GIL\" → cast Python arg to C type before nogil block\n- \"missing 1 required positional argument\" → use `def func(n=1000):` not typed default\n- \"Expected an identifier or literal\" → check for stray `}` after functions\n- \"Syntax error in C variable declaration\" → move array init inside function\n\n## OPTIMIZATION PATTERNS\n\n### Replace Python lists with C arrays\n```cython\ncdef int *dp = <int *>malloc((n + 1) * sizeof(int))\nmemset(dp, 0, (n + 1) * sizeof(int))\n# ... use dp[i] instead of list[i] ...\nfree(dp)\n```\n\n### Sorting with qsort\n```cython\ncdef int cmp_func(const void *a, const void *b) noexcept nogil:\n    return (<int *>a)[0] - (<int *>b)[0]\nqsort(arr, n, sizeof(int), cmp_func)\n```\n\n### C math instead of Python math\n```cython\nfrom libc.math cimport sin, cos, sqrt, M_PI\n# Direct C calls, no Python overhead\n```\n\n### Precompute outside loops\n```cython\ncdef double inv_n = 1.0 / n\nfor i in range(n):\n    result += values[i] * inv_n  # multiply instead of divide\n```\n\n## ITERATIVE PROCESS\n\n1. **Write**: Translate Python to Cython with basic `cdef` types and correct algorithm\n2. **Evaluate**: Call evaluate_cython — read ALL feedback sections\n3. **Fix compilation errors** first (nothing else matters until it compiles)\n4. **Fix test failures** next (correctness before performance)\n5. **Improve annotation score** — add more `cdef`, replace Python constructs with C\n6. **Maximize speedup** — use malloc arrays, nogil, precompute constants\n7. **Evaluate again** until all criteria are met",
      "fields": [
        {
          "prefix": "Python Code:",
          "description": "The Python source code to optimize"
        },
        {
          "prefix": "Func Name:",
          "description": "Name of the main function to optimize"
        },
        {
          "prefix": "Description:",
          "description": "Description of what the code does"
        },
        {
          "prefix": "Trajectory:",
          "description": "${trajectory}"
        },
        {
          "prefix": "Reasoning: Let's think step by step in order to",
          "description": "${reasoning}"
        },
        {
          "prefix": "Cython Code:",
          "description": "Complete .pyx Cython source code"
        }
      ]
    },
    "lm": null
  },
  "metadata": {
    "dependency_versions": {
      "python": "3.12",
      "dspy": "3.1.3",
      "cloudpickle": "3.1"
    }
  }
}
